setup.py
snap/__init__.py
snap/adapter.py
snap/app.py
snap/configure.zcml
snap/content.py
snap/directory.py
snap/interface.py
snap/makefile.in
snap/metadata.py
snap/paste.ini.in
snap/publication.py
snap/registry.py
snap/utils.py
snap.egg-info/PKG-INFO
snap.egg-info/SOURCES.txt
snap.egg-info/dependency_links.txt
snap.egg-info/not-zip-safe
snap.egg-info/top_level.txt
snap/browser/__init__.py
snap/browser/configure.zcml
snap/browser/macros.py
snap/browser/main_template.pt
snap/browser/metadata.pt
snap/browser/style.css
snap/browser/view.py
snap/docs/DESIGN.txt
snap/docs/README.txt
snap/docs/REQUIREMENTS.txt
snap/exceptions/__init__.py
snap/exceptions/configure.zcml
snap/exceptions/error_debug.pt
snap/exceptions/exceptions.py
snap/exceptions/not_found.pt
snap/exceptions/unauthorized.pt
snap/filter/__init__.py
snap/filter/config.py
snap/filter/xslt.py
snap/path/__init__.py
snap/tests/__init__.py
snap/tests/security.txt
snap/tests/test_security.py
