Metadata-Version: 1.0
Name: snap
Version: 0.5
Summary: snap - zope 3 frontend for entransit
Home-page: http://cheeseshop.python.org/pypi/snap
Author: Sidnei da Silva
Author-email: sidnei@enfoldsystems.com
License: Lesser General Public License (LGPL)
Download-URL: http://cheeseshop.python.org/packages/source/s/snap/snap-0.5.tar.gz
Keywords: web wsgi application server
Platform: any
Classifier: Development Status :: 3 - Alpha
Classifier: Environment :: Web Environment
Classifier: License :: OSI Approved :: GNU Library or Lesser General Public License (LGPL)
Classifier: Operating System :: OS Independent
Classifier: Programming Language :: Python
Classifier: Topic :: Internet :: WWW/HTTP
Classifier: Topic :: Software Development :: Libraries :: Python Modules
